mcp_ocrai/__init__.py
mcp_ocrai/__main__.py
mcp_ocrai/main.py
mcp_ocrai/services/__init__.py
mcp_ocrai/services/document.py
mcp_ocrai/services/file_type.py
mcp_ocrai/utils/parse_pages.py
mcp_ocrai-0.3.0.dist-info/licenses/LICENSE.txt
mcp_ocrai-0.3.0.dist-info/METADATA
mcp_ocrai-0.3.0.dist-info/WHEEL
mcp_ocrai-0.3.0.dist-info/entry_points.txt
mcp_ocrai-0.3.0.dist-info/top_level.txt
mcp_ocrai-0.3.0.dist-info/RECORD
