Metadata-Version: 2.4
Name: mcp-ocrai
Version: 0.3.0
Summary: A MCP server for OCR files using Mistral API
Project-URL: Homepage, https://github.com/pedrxd/mcp-ocrai
Project-URL: Issues, https://github.com/pedrxd/mcp-ocrai/issues
Requires-Python: >=3.12
License-File: LICENSE.txt
Requires-Dist: fastmcp>=2.14.1
Requires-Dist: mistralai>=1.9.11
Dynamic: license-file
